libinput_gestures_qt/__init__.py
libinput_gestures_qt/edit_window.py
libinput_gestures_qt/main.py
libinput_gestures_qt/main_window.py
libinput_gestures_qt/logo/libinput-gestures-qt.desktop
libinput_gestures_qt/logo/libinput-gestures-qt.png
libinput_gestures_qt-0.4.data/data/local/share/applications/libinput-gestures-qt.desktop
libinput_gestures_qt-0.4.data/data/local/share/pixmaps/libinput-gestures-qt.png
libinput_gestures_qt-0.4.data/data/share/applications/libinput-gestures-qt.desktop
libinput_gestures_qt-0.4.data/data/share/pixmaps/libinput-gestures-qt.png
libinput_gestures_qt-0.4.data/scripts/libinput-gestures-qt
libinput_gestures_qt-0.4.dist-info/LICENSE.md
libinput_gestures_qt-0.4.dist-info/METADATA
libinput_gestures_qt-0.4.dist-info/WHEEL
libinput_gestures_qt-0.4.dist-info/top_level.txt
libinput_gestures_qt-0.4.dist-info/RECORD
