Metadata-Version: 2.1
Name: libinput-gestures-qt
Version: 0.4
Summary: Qt interface for libinput-gestures (works best with Plasma)
Home-page: https://github.com/OneAdder/libinput_gestures_qt
Author: Michael Voronov
Author-email: mikivo@list.ru
License: GPLv3
Platform: UNKNOWN
